{
  "meta": {
    "version": "1.0.0",
    "updated": "2026-06-29",
    "source": "商談文字起こし分析 — MEDDPICC カード",
    "note": "FAQ分離 — faqIds参照（35枚）。faq.json v1.1.0",
    "cards": 44,
    "withFaqIds": 35,
    "faq": "public/faq.json"
  },
  "cards": [
    {
      "shelf": "I",
      "scene": "非課税枠拡大が問い合わせの引き金",
      "quote": "3,500円だったらインパクトないよね…7,500円になるから",
      "speaker": "経営者・人事",
      "speakerRead": "これは希望ではなくCE（2026年4月という動かせない期限）",
      "read": "最強のコンペリングイベント。「いつか」ではなく4月施行が動く理由。動機は既にある。",
      "doIt": "4月施行を起点に逆算スケジュール。「第三の賃上げ」としてEBの言語に翻訳して渡す。",
      "dont": "製品説明から入る（動機が既にあるので不要、熱を冷ます）。",
      "freq": "高（~150件）",
      "status": "proven",
      "sources": [
        {
          "label": "国税庁 No.2594-1 非課税限度額の判定",
          "url": "https://www.nta.go.jp/taxes/shiraberu/taxanswer/gensen/2594-1.htm"
        },
        {
          "label": "エデンレッド公式 チケットレストラン",
          "url": "https://edenred.jp/ticketrestaurant/"
        }
      ],
      "faqIds": [
        "Q01"
      ]
    },
    {
      "shelf": "I",
      "scene": "賃上げの代替として検討している",
      "quote": "5,000円上げても手元には3,500円しか行かない",
      "speaker": "経営者",
      "speakerRead": "賃上げ予算が既にある＝予算化済みのサイン。価格の壁が低い",
      "read": "福利厚生予算ではなく賃上げ予算に乗る案件。手取り差が刺さる。",
      "doIt": "「賃上げ総コスト vs チケレス総コスト」で手取り差を可視化（5,000円昇給→手取り+3,500円 ／ 7,500円補助→手取り+7,500円）。",
      "dont": "福利厚生としてだけ売る（賃上げ予算に乗せ損ねる）。",
      "freq": "高（~120件）",
      "status": "proven",
      "faqIds": [
        "Q01",
        "Q14"
      ]
    },
    {
      "shelf": "I",
      "scene": "既存の福利厚生が使われていない",
      "quote": "月額だけ払っていて、正直、私も1回も使ったことがない",
      "speaker": "人事・総務",
      "speakerRead": "競合パッケージへの不満が入口＝切替の動機が既にある",
      "read": "リロ／ベネワン等の低利用率への不満。切替動機が顧客側に既にある。",
      "doIt": "「使われない福利厚生 vs 利用率98%」。切替でなく“併用”として提案し抵抗を下げる。",
      "dont": "既存ベンダーを正面から否定する（顧客の選定責任を否定することになる）。",
      "freq": "中（~50件）",
      "status": "proven",
      "sources": [
        {
          "label": "エデンレッド公式 選ばれる理由（利用率98%）",
          "url": "https://edenred.jp/ticketrestaurant/about"
        }
      ]
    },
    {
      "shelf": "DC",
      "scene": "手数料10%が高いと言う",
      "quote": "10パーは高いな。それなら法人税を払っておいた方がいいんじゃないか",
      "speaker": "経営者・財務",
      "speakerRead": "原価で語り出したらEB（決裁者）が関与しているサイン",
      "read": "価格単独ではなく「コストを正当化する材料」を探している。最大の障壁（最頻出）。",
      "doIt": "1人あたり手数料1,500円（15,000円×10%）。非課税ウェッジ（所得税10%＋住民税10% ≒ +1,500円/人）と税効果はおおむね相殺 → ネット±0円/人・月（社保は前提に含めない）。オールイン（システム・25万店決済網・カード・サポート・不正監視）。大企業向けボリュームDCあり。比較は月額単価でなく総コスト（Q07）。",
      "dont": "「安いです／お得です」と値頃感で押す／月額単価だけで比較させる（総コストで見せる）。",
      "freq": "高（~140件）",
      "status": "proven",
      "faqIds": [
        "Q05"
      ]
    },
    {
      "shelf": "DC",
      "scene": "非課税は本当に大丈夫か確認",
      "quote": "非課税って本当に大丈夫？税務署に指摘されないですか？",
      "speaker": "人事＝情報収集／財務・役員＝決裁ゲート",
      "speakerRead": "誰が言ったかで意味が真逆になる",
      "read": "要件を満たせば非課税は明確。曖昧に断定すると、かえって不信を招く。",
      "doIt": "非課税の2要件（本人負担50%以上＋会社負担が月額上限内）を満たせば会社負担分が非課税、と要件で示す。現金支給は全額課税。最終判断は顧客側専門家。",
      "dont": "「多分大丈夫です」「一般的には問題ないです」（禁句）／要件に触れず断定する。",
      "freq": "高（FAQ最頻）",
      "status": "proven",
      "sources": [
        {
          "label": "国税庁 No.2594 食事を支給したとき",
          "url": "https://www.nta.go.jp/taxes/shiraberu/taxanswer/gensen/2594.htm"
        },
        {
          "label": "国税庁 No.2594-1 非課税限度額の判定",
          "url": "https://www.nta.go.jp/taxes/shiraberu/taxanswer/gensen/2594-1.htm"
        },
        {
          "label": "社内：提案デッキ Q01／付録A",
          "url": null
        }
      ],
      "faqIds": [
        "Q01"
      ]
    },
    {
      "shelf": "DC",
      "scene": "社会保険料への算入を心配する",
      "quote": "社保にかかっちゃったら、あんまり意味がない",
      "speaker": "税理士・会計事務所・経理",
      "speakerRead": "士業・経理が出したら決裁ゲート。曖昧回答が一番効かない",
      "read": "ROIは所得税・住民税の非課税効果で成立する論点。社保削減を前提にすると断定できず、かえって弱くなる。",
      "doIt": "ROIは所得税の非課税だけで成立すると示す。報酬該当性は実態（公平性・恒常性・現金代替性）で判断され、最終は顧問社労士・所轄年金事務所の見解と整理（健保法第3条第5項）。",
      "dont": "「2/3負担なら非算入」等の断定／社保の非算入を前提にROIを語る（デッキ方針に反する）。",
      "freq": "高（~60件）",
      "status": "proven",
      "sources": [
        {
          "label": "日本年金機構 現物給与の価額",
          "url": "https://www.nenkin.go.jp/service/kounen/hokenryo/hoshu/20150511.html"
        },
        {
          "label": "日本年金機構 報酬の範囲",
          "url": "https://www.nenkin.go.jp/service/kounen/hokenryo/hoshu/20150515-01.html"
        },
        {
          "label": "社内：提案デッキ S26／付録B",
          "url": null
        }
      ],
      "faqIds": [
        "Q04"
      ]
    },
    {
      "shelf": "DC",
      "scene": "不正利用（タバコ・酒・日用品）を懸念",
      "quote": "品名がブロックできない、というのを経営陣がどう思うか",
      "speaker": "人事・経営陣",
      "speakerRead": "経営陣の“体面リスク”。ゼロ化要求か抑止で足りるかを見極める",
      "read": "完全な不正ゼロを求めているのではなく、社内で説明できる抑止を求めている。",
      "doIt": "管理ポータルで利用可視化・カード即時停止。規程で食事以外禁止＋量・頻度モニタリング。OCRで対象外利用検知時は課税対象額をCSV提供（いーウェル連携）。完全防止は困難と正直に説明し、統制・証跡で抑止。",
      "dont": "「はっきり言うとバレないですよ」と運用の緩さを売りにする（信頼を落とす）。",
      "freq": "高（~110件）",
      "status": "proven",
      "sources": [
        {
          "label": "エデンレッド公式 チケットレストラン",
          "url": "https://edenred.jp/ticketrestaurant/"
        }
      ],
      "faqIds": [
        "Q02",
        "Q10"
      ]
    },
    {
      "shelf": "DC",
      "scene": "天引きで手取りが減って見える",
      "quote": "自分の分を足すよ、となると“うん…”という人もいると思う",
      "speaker": "人事・現場",
      "speakerRead": "金額の問題ではなく“見え方”と従業員心理の問題",
      "read": "制度の損得ではなく、給与明細上の見え方で止まっている。",
      "doIt": "給与天引き（賃金控除）で本人負担50%以上を精算。労基法第24条の例外として労使協定が必要（ひな型提供・締結支援）。天引き前後の手取り比較を図解し「実質手取りが増える」を示す。必要なら説明会を代行。",
      "dont": "「すぐ慣れますよ」で流す。",
      "freq": "中（~90件）",
      "status": "proven",
      "sources": [
        {
          "label": "労働基準法 第24条（e-Gov）",
          "url": "https://laws.e-gov.go.jp/law/322AC0000000049"
        }
      ],
      "faqIds": [
        "Q06"
      ]
    },
    {
      "shelf": "DC",
      "scene": "地方で使える店が少ないと言う",
      "quote": "コンビニぐらいはありますけど…",
      "speaker": "地方拠点の担当者",
      "speakerRead": "即答できないと一気に熱が冷める実利確認",
      "read": "地方顧客の“本当に使えるのか”の確認。曖昧だと前進しない。",
      "doIt": "所在地周辺の利用可能店舗を事前リスト化。2026年8月のMC切替で拡大見通しを説明。北海道はセイコーマート対応と即答。",
      "dont": "「コンビニはあります」で曖昧に流す。",
      "freq": "中（~50件）",
      "status": "proven",
      "faqIds": [
        "Q08"
      ]
    },
    {
      "shelf": "CO",
      "scene": "miiveと比較している",
      "quote": "使った分だけ請求という形が良さそう",
      "speaker": "購買・人事",
      "speakerRead": "後払いの手軽さに見えている。レシート必須の運用負荷が隠れた弱点",
      "read": "後払い精算が魅力に映っているが、レシート提出必須の運用煩雑さに気づいていない。",
      "doIt": "「前払い(プリペイド) vs 後払い精算」の根本差を冒頭で明確化。39年・国内約4,000社・全国25万店＋Uber Eats・レシート提出任意を訴求。",
      "dont": "機能の細部比較に入る（土俵を相手に渡す）。",
      "freq": "高（最多言及）",
      "status": "proven",
      "sources": [
        {
          "label": "エデンレッド公式 会社情報（4,000社／25万店）",
          "url": "https://edenred.jp/"
        },
        {
          "label": "エデンレッド公式 チケットレストラン",
          "url": "https://edenred.jp/ticketrestaurant/"
        }
      ],
      "faqIds": [
        "Q07",
        "Q15"
      ]
    },
    {
      "shelf": "CO",
      "scene": "HQの固定手数料が安く見える",
      "quote": "月額500円が安い／20名以下はダメと書いてあった",
      "speaker": "小規模企業の担当者",
      "speakerRead": "規模で従量/固定の損得は変わる。HQは20名以下非対応が弱点",
      "read": "固定費が安く見えるが、20名以下なら即優位に立てる場面。",
      "doIt": "規模別に従量/固定の損益分岐を示す。20名以下は即優位。比較は月額単価でなく総コスト（管理工数・カバレッジ・継続性）で。25万店＋Uber Eatsで全社員に届く。",
      "dont": "月額単価だけで張り合う。",
      "freq": "中",
      "status": "proven",
      "sources": [
        {
          "label": "エデンレッド公式 選ばれる理由（利用率98%）",
          "url": "https://edenred.jp/ticketrestaurant/about"
        }
      ],
      "faqIds": [
        "Q07"
      ]
    },
    {
      "shelf": "CO",
      "scene": "リロクラブ/ベネワンと併存している",
      "quote": "リロさんからも食事補助の案内が来ていたんですけど",
      "speaker": "人事・総務",
      "speakerRead": "パッケージ福利厚生は利用率1-2割で潜在的に不満",
      "read": "既存パッケージの低利用率が切替の入口。ただし正面否定は禁物。",
      "doIt": "「利用率98% vs 1-2割」。切替でなく“併用”提案で抵抗を下げる。",
      "dont": "既存契約を全否定して切替を迫る。",
      "freq": "中",
      "status": "proven",
      "sources": [
        {
          "label": "エデンレッド公式 選ばれる理由（利用率98%）",
          "url": "https://edenred.jp/ticketrestaurant/about"
        }
      ],
      "faqIds": [
        "Q07"
      ]
    },
    {
      "shelf": "E",
      "scene": "税務最適化の論理で語り出す",
      "quote": "どうせ払うお金が一緒なら、非課税枠の方が実入りがいいよね",
      "speaker": "経営者・財務",
      "speakerRead": "ROIでなく税務最適で考えるEBが表に出たサイン",
      "read": "費用対効果でなく税務的有利性で意思決定するタイプ。ここに合わせると速い。",
      "doIt": "社保15%・賃上げ総コストと並べ、税務的に有利な点を経営者の言語で示す。",
      "dont": "福利厚生の情緒的価値で押す。",
      "freq": "中",
      "status": "proven",
      "faqIds": [
        "Q01"
      ]
    },
    {
      "shelf": "E",
      "scene": "院長・事務長が税務に踏み込む（医療）",
      "quote": "お昼ご飯代はもう課税対象だから、という思い込みがあって",
      "speaker": "院長・事務長",
      "speakerRead": "税務理解が高い決裁者。誤認を解けば一気に進む",
      "read": "知識ゆえの誤認で止まっている。正しく解けば信頼ごと前進する。",
      "doIt": "国税庁通達を引用し、非課税の2要件（本人50%以上負担・食事限定）を満たせば食事補助は非課税、と正す。1枚資料で。",
      "dont": "通達を示さず口頭で「非課税です」と断言する。",
      "freq": "中",
      "status": "proven",
      "sources": [
        {
          "label": "国税庁 No.2594 食事を支給したとき",
          "url": "https://www.nta.go.jp/taxes/shiraberu/taxanswer/gensen/2594.htm"
        },
        {
          "label": "社内：提案デッキ Q01／付録A",
          "url": null
        }
      ],
      "faqIds": [
        "Q01"
      ]
    },
    {
      "shelf": "E",
      "scene": "決裁者が事前学習を済ませている",
      "quote": "もう以前から興味があって。ぜひ使わせてもらおうと思います",
      "speaker": "社長（YouTube/FBで学習済み）",
      "speakerRead": "事前理解が深い＝意思決定が速い。遅延が最大の機会損失",
      "read": "EBが学習済みで決裁者同席。その場で締められる即決サイン。",
      "doIt": "決裁者同席を確認し、満額＋キャンペーンを即提示してその場でクロージング（即日登録まで）。",
      "dont": "一から説明し直して熱を冷ます。",
      "freq": "中（即決15件+）",
      "status": "proven"
    },
    {
      "shelf": "M",
      "scene": "費用対効果の根拠を求められる",
      "quote": "手数料を払ってでも見合うのか",
      "speaker": "財務・経営",
      "speakerRead": "手数料を上回る価値の“数字での言語化”を求めている",
      "read": "定性メリットでは納得しない。定量比較を欲している。",
      "doIt": "賃上げ手取り比較＋利用率98%＋採用差別化を規模別(100/300/500名)で定量化。",
      "dont": "定性メリットだけを並べる。",
      "freq": "中",
      "status": "hyp",
      "faqIds": [
        "Q05"
      ]
    },
    {
      "shelf": "M",
      "scene": "目的が朝食なら満額は過剰",
      "quote": "朝食には（15,000円は）かけないでしょう",
      "speaker": "人事",
      "speakerRead": "目的が限定的＝満額提案が逆効果になる場面",
      "read": "健康経営・朝食目的の顧客に満額を押すと過剰でズレる。",
      "doIt": "目的（朝食/健康経営）に金額を合わせる。満額に固執しない。",
      "dont": "一律で満額(15,000円)を押す。",
      "freq": "中",
      "status": "proven"
    },
    {
      "shelf": "CH",
      "scene": "社労士・税理士が推進者になる",
      "quote": "シンプルさが決め手。勉強会にも登壇してほしい",
      "speaker": "社労士・税理士",
      "speakerRead": "士業が理解すると顧問先への横展開が見込める高価値チャンピオン",
      "read": "一社の成約に留めると横展開を逃す。士業は紹介ハブになる。",
      "doIt": "シンプルさを決め手に成約し、勉強会・顧問先紹介まで設計する。",
      "dont": "単発の成約で完結させる。",
      "freq": "中（成約→展開実績あり）",
      "status": "proven"
    },
    {
      "shelf": "CH",
      "scene": "現場の本音を率直に語る担当者",
      "quote": "はっきり言うと、底辺の人種が多くて…",
      "speaker": "現場マネージャー",
      "speakerRead": "本音を出す＝信頼されているチャンピオン候補",
      "read": "率直さは敵意ではなく信頼のサイン。味方化の好機。",
      "doIt": "従業員説明会を営業が代行する提案で、推進者の社内負担を下げて味方化する。",
      "dont": "率直な発言を額面通り受けて現場の懸念を軽視する。",
      "freq": "低",
      "status": "hyp"
    },
    {
      "shelf": "DP",
      "scene": "「また連絡します」で終わりそう",
      "quote": "資料、いったん送っておいてもらえますか",
      "speaker": "担当者全般",
      "speakerRead": "次アクション未確定＝失注の最頻ルート",
      "read": "温度感はあるのに次の一手が無い。ここで多くが流れる。",
      "doIt": "商談中に必ず具体的な日付を設定して終わる（次回確定型）。",
      "dont": "「資料送ります」「また連絡します」で締める。",
      "freq": "高",
      "status": "proven",
      "faqIds": [
        "Q13"
      ]
    },
    {
      "shelf": "DP",
      "scene": "事前学習済みで即決できる状態",
      "quote": "YouTubeで見て、だいたい分かってます",
      "speaker": "社長・決裁者",
      "speakerRead": "認知が高い状態（FB/YouTube経由）は即日登録まで行ける",
      "read": "理解が深い顧客に説明を尽くすのは逆効果。クロージングへ。",
      "doIt": "面談内でアカウント登録完了まで誘導（即日成約パターン）。",
      "dont": "「持ち帰って検討」を許す。",
      "freq": "中（即日成約15件+）",
      "status": "proven",
      "faqIds": [
        "Q13"
      ]
    },
    {
      "shelf": "PP",
      "scene": "プリペイド方式を後で知って拒否",
      "quote": "チャージしなければいけないというのがダメで",
      "speaker": "担当者",
      "speakerRead": "支払い方式の認識ズレ。長い説明の後に発覚すると全損",
      "read": "前払い方式への抵抗。後で出ると、それまでの商談が無駄になる。",
      "doIt": "冒頭で「前払い(プリペイド)方式」であることを確認するスクリプトを徹底。",
      "dont": "方式の確認を後回しにして説明を進める。",
      "freq": "中",
      "status": "proven"
    },
    {
      "shelf": "PP",
      "scene": "経費処理・仕訳を問われる",
      "quote": "これ、福利厚生費ですか？預かり金ですか？仕訳は？",
      "speaker": "経理",
      "speakerRead": "経理が握っているサイン。実務障壁",
      "read": "導入実務の最後の関門。経理が止めると進まない。",
      "doIt": "チャージ時・天引き時の仕訳サンプルを即提示する。",
      "dont": "「経理さんにお任せください」で流す。",
      "freq": "中",
      "status": "hyp",
      "faqIds": [
        "Q18"
      ]
    },
    {
      "shelf": "CO",
      "scene": "置き型社食から乗り換え検討",
      "quote": "余りが出てきていて。4箇所あると冷蔵庫も4台",
      "speaker": "総務（おかん等 利用中）",
      "speakerRead": "外勤者に届かず不公平・廃棄が出る＝乗換動機が既にある",
      "read": "置き型は設置場所に縛られ、現場/外勤に届かず廃棄も出る。不満が入口。",
      "doIt": "「場所を選ばない／外勤・在宅・出張対応／廃棄が出ない」の3点で優位を示す。",
      "dont": "価格や品揃えで比較する（土俵を間違える）。",
      "freq": "中",
      "status": "proven",
      "sources": [
        {
          "label": "エデンレッド公式 選ばれる理由（利用率98%）",
          "url": "https://edenred.jp/ticketrestaurant/about"
        }
      ],
      "faqIds": [
        "Q08",
        "Q14",
        "Q21"
      ]
    },
    {
      "shelf": "CO",
      "scene": "仕出し弁当と併用を検討",
      "quote": "今の弁当と一緒に使えるのか、非課税枠は共有になる？",
      "speaker": "人事・総務",
      "speakerRead": "排他でなく併用前提＝抵抗が低い",
      "read": "既存制度の置き換えに身構えているが、実は併用で非課税枠を最大化できる。",
      "doIt": "「選択の自由度＋併用で非課税枠を最大活用」。併用時の枠計算シートで示す。",
      "dont": "既存弁当の置き換えを迫る。",
      "freq": "低",
      "status": "proven",
      "faqIds": [
        "Q21"
      ]
    },
    {
      "shelf": "DC",
      "scene": "スマホ決済の時期を気にする",
      "quote": "アプリ決済はいつ？物理カードが要らなくなるのは？",
      "speaker": "情シス・担当者",
      "speakerRead": "将来性で迷っている。ロードマップ提示が安心材料になる",
      "read": "今の不便さでなく「先細りしないか」を確認している。未定回答だと冷める。",
      "doIt": "当面はプリペイドカード（iDタッチ）。アプリで残高・履歴・加盟店検索・利用停止・証憑スキャン。モバイル決済は今後対応予定—導入時に最新ロードマップを提示。",
      "dont": "「まだ未定です」で止める。",
      "freq": "中",
      "status": "proven",
      "faqIds": [
        "Q12"
      ]
    },
    {
      "shelf": "DC",
      "scene": "残高繰越・有効期限を確認",
      "quote": "使わなかった分は翌月に持ち越せるんですか？",
      "speaker": "担当者・従業員",
      "speakerRead": "損したくない心理。軽い論点だが放置すると不信に育つ",
      "read": "制度の損得を細かく確認するフェーズ。図解で即解消できる。",
      "doIt": "1日上限2,500円／残高有効期限1年／対象は飲食物のみ（アルコール・タバコ等は対象外）。FAQ図解で即答。国税庁在宅勤務FAQ問12に沿う設計と説明。",
      "dont": "口頭の説明だけで流す。",
      "freq": "中",
      "status": "proven",
      "faqIds": [
        "Q09"
      ]
    },
    {
      "shelf": "DC",
      "scene": "パート・アルバイトの対象範囲",
      "quote": "週20時間未満は除外できますか？合理的な基準は？",
      "speaker": "人事",
      "speakerRead": "公平性と人件費の線引き。合理的基準の根拠を求めている",
      "read": "「自由に決められます」では不安。社内で説明できる基準が欲しい。",
      "doIt": "2要件に「全員対象」の明文はないが公平な設計を強推。雇用形態ごとの取扱いを規程に明文化。特定部署・役職のみ優遇は給与認定リスク。合理的区分の根拠チャートで社内説明可能に。",
      "dont": "「自由に決められます」だけで終える。",
      "freq": "中",
      "status": "proven",
      "faqIds": [
        "Q03"
      ]
    },
    {
      "shelf": "PP",
      "scene": "退職時の取扱いを確認",
      "quote": "退職者のカードは回収しますか？残高はどうなる？",
      "speaker": "総務",
      "speakerRead": "運用責任の懸念。総務が止めると進まない実務論点",
      "read": "導入後の運用負荷を測っている。曖昧だと「面倒そう」で止まる。",
      "doIt": "退職フロー図の標準資料で即答（回収・残高処理を明示）。",
      "dont": "「都度対応で」と曖昧にする。",
      "freq": "中",
      "status": "proven",
      "faqIds": [
        "Q16"
      ]
    },
    {
      "shelf": "M",
      "scene": "健康経営の効果を数字で求める",
      "quote": "健康経営として、実際に効果は出るんですか？",
      "speaker": "人事・経営",
      "speakerRead": "健康経営文脈は定量データが効く",
      "read": "福利厚生の一般論では動かない。健康面の定量根拠を欲している。",
      "doIt": "朝食欠食改善率などの健康経営データを提示し、施策の効果を数字で裏づける。",
      "dont": "食事補助の一般的メリットで返す。",
      "freq": "中",
      "status": "hyp"
    },
    {
      "shelf": "I",
      "scene": "建設・電気工事業からの相談",
      "quote": "現場が直行直帰で、コンビニくらいしか寄れなくて",
      "speaker": "経営者・人事（建設業）",
      "speakerRead": "最も導入適性が高い業界。コンビニが唯一の補給源＝最大訴求",
      "read": "現場直行直帰・人手不足・公平性。置き型は届かないがチケレスは全員平等。",
      "doIt": "「全員平等・現場に届く・コンビニ対応」を軸に、置き型との差で攻める。",
      "dont": "オフィス前提の説明をする。",
      "freq": "中（問い合わせ業界1-2位）",
      "status": "proven",
      "sources": [
        {
          "label": "エデンレッド公式 導入事例",
          "url": "https://edenred.jp/ticketrestaurant/cases"
        }
      ],
      "faqIds": [
        "Q08"
      ]
    },
    {
      "shelf": "I",
      "scene": "医療・歯科・介護からの相談",
      "quote": "職種も食事の時間もバラバラで、公平にしたくて",
      "speaker": "院長・事務長",
      "speakerRead": "多職種・多拠点は「公平に使える」が刺さる",
      "read": "勤務形態がバラバラで、全員が等しく使える点が決め手になる。",
      "doIt": "時間・場所を問わず全員が使える公平性を訴求。税務理解が高い前提で通達も用意。",
      "dont": "社食型と同列に説明する。",
      "freq": "中",
      "status": "proven",
      "sources": [
        {
          "label": "エデンレッド公式 導入事例",
          "url": "https://edenred.jp/ticketrestaurant/cases"
        }
      ],
      "faqIds": [
        "Q08"
      ]
    },
    {
      "shelf": "I",
      "scene": "IT・情報サービスの出社推進",
      "quote": "北風よりは太陽みたいな形で、出社を促せたら",
      "speaker": "人事（IT企業）",
      "speakerRead": "出社施策として柔らかく使える文脈",
      "read": "強制でなく誘導で出社を促したい。食事補助が“太陽”の施策になる。",
      "doIt": "在宅/出社でチャージ額を変える運用を提案。テレワークはUberEats、外回りはコンビニ両対応を示す。",
      "dont": "一律運用だけを示す。",
      "freq": "低",
      "status": "hyp"
    },
    {
      "shelf": "DC",
      "scene": "監査で何を見られるか問う",
      "quote": "監査で説明できますか？証憑はどう担保しますか？",
      "speaker": "内部監査・経理",
      "speakerRead": "統制を握る部門。曖昧回答は決裁を止める",
      "read": "主論点は「支出の正当性」と「運用統制」。説明できる形そのものを求めている。",
      "doIt": "制度前提・運用ルール・権限設計を整理し「監査で説明できる運用フロー」として提示。",
      "dont": "「監査は気にしなくていいです」（禁句）。",
      "freq": "中",
      "status": "proven",
      "faqIds": [
        "Q10"
      ]
    },
    {
      "shelf": "DC",
      "scene": "情シスが個人情報・権限を問う",
      "quote": "個人情報やセキュリティはどうなっていますか？",
      "speaker": "情シス",
      "speakerRead": "情シスが論点を持つと別の決裁ゲートになる",
      "read": "論点はデータ範囲・権限管理・ログ・委託先管理。営業の言葉では通らない。",
      "doIt": "日常運用はポータルでカード注文・チャージが中心。特別なシステム連携・情シス対応は基本不要。情シス向けにデータ範囲・権限・ログ・委託先管理の説明資料を用意。",
      "dont": "営業トークで「安全です」と流す。",
      "freq": "中",
      "status": "proven",
      "faqIds": [
        "Q11"
      ]
    },
    {
      "shelf": "DC",
      "scene": "資金決済法の観点を問う",
      "quote": "資金決済法の観点は問題ないですか？",
      "speaker": "法務・経理",
      "speakerRead": "法務が関与＝慎重ゲート。断定は禁物",
      "read": "論点は「該当スキーム」「運用留意」「顧客としての説明責任」。",
      "doIt": "顧客の社内説明に必要なポイント（該当スキーム・運用留意・説明責任）を整理して情報提供。",
      "dont": "その場で「問題ありません」と断定的に言い切る。",
      "freq": "低",
      "status": "proven",
      "sources": [
        {
          "label": "資金決済に関する法律（e-Gov）",
          "url": "https://laws.e-gov.go.jp/law/421AC0000000059"
        }
      ]
    },
    {
      "shelf": "PP",
      "scene": "1日の利用限度額を確認",
      "quote": "1日の利用限度額は？あとから変更できますか？",
      "speaker": "総務・人事",
      "speakerRead": "運用設計の確認。軽いが即答できないと不信に育つ",
      "read": "制度を自社に合わせられるかの確認。設定の柔軟性を見ている。",
      "doIt": "1日の利用上限2,500円。チャージ残高の有効期限1年。対象は飲食物に限定。限度額設定ガイドで標準値・変更可否を即答。",
      "dont": "「店舗や設定によります」で曖昧に流す。",
      "freq": "中",
      "status": "proven",
      "faqIds": [
        "Q09"
      ]
    },
    {
      "shelf": "PP",
      "scene": "残高不足時の併用決済を確認",
      "quote": "残高が足りないとき、現金やカードと併用できますか？",
      "speaker": "担当者・従業員",
      "speakerRead": "実利用のイメージ確認。生活動線に乗るかを見ている",
      "read": "日常で本当に使えるかの確認。チェーンごとの可否が気になる。",
      "doIt": "主要チェーン対応表で併用可否を即答する。",
      "dont": "「店舗によります」だけで終える。",
      "freq": "中",
      "status": "proven",
      "faqIds": [
        "Q17"
      ]
    },
    {
      "shelf": "PP",
      "scene": "マスターカード切替の影響を確認",
      "quote": "いつMCに切り替わりますか？自販機は使えなくなる？",
      "speaker": "情シス・総務",
      "speakerRead": "既存利用の継続性への不安",
      "read": "今使えているものが使えなくなる不安。切替＝拡大の機会と伝えたい。",
      "doIt": "MC切替FAQ資料で、利用可能店舗の大幅拡大と移行スケジュールを示す。",
      "dont": "「未定です」で止める。",
      "freq": "中",
      "status": "proven",
      "faqIds": [
        "Q22"
      ]
    },
    {
      "shelf": "PP",
      "scene": "家族の食事に使えるか問う",
      "quote": "家族の食事や、家族とのレストランでも使えますか？",
      "speaker": "担当者・従業員",
      "speakerRead": "制度趣旨の誤解。放置するとコンプラリスクが残る",
      "read": "「本人の食事」が制度の前提。曖昧にすると後で運用が崩れる。",
      "doIt": "利用ガイドラインで「本人の食事補助」という原則と線引きを明確に示す。",
      "dont": "曖昧にして“何にでも使える”印象を残す。",
      "freq": "低",
      "status": "proven",
      "faqIds": [
        "Q20"
      ]
    },
    {
      "shelf": "I",
      "scene": "運輸・物流からの相談",
      "quote": "ドライバーが長距離で年100日以上不在のこともあって",
      "speaker": "経営者・人事（運輸物流）",
      "speakerRead": "出先のコンビニ・FFが昼食中心＝出張者に届く点が刺さる",
      "read": "長距離・直行直帰で社食も置き型も届かない。出先で使える点が決め手。",
      "doIt": "出張・出先のコンビニ等で使える点を訴求。全員に等しく届く設計を示す。",
      "dont": "オフィス・拠点前提で説明する。",
      "freq": "低",
      "status": "proven",
      "sources": [
        {
          "label": "エデンレッド公式 導入事例",
          "url": "https://edenred.jp/ticketrestaurant/cases"
        }
      ],
      "faqIds": [
        "Q08"
      ]
    },
    {
      "shelf": "DP",
      "scene": "全社展開の進め方を確認（FAQ Q13）",
      "quote": "いきなり全社一括だと反対が出そう…段階的にできますか？",
      "speaker": "人事・経営",
      "speakerRead": "全社展開への不安。段階ロールアウトの具体像を求めている",
      "read": "一括＝リスクと誤解しがち。設計→検証→稟議→ロールアウトの型があると安心する。",
      "doIt": "Phase1制度設計→Phase2効果検証→Phase3稟議支援→Phase4拠点別ロールアウト（計5〜7ヶ月目安）。実データで役員・労組説明。ERJが伴走。",
      "dont": "「全社一括必須」と圧力をかける／具体フェーズなしで「大丈夫です」と流す。",
      "freq": "中（デッキFAQ）",
      "status": "proven",
      "faqIds": [
        "Q13"
      ]
    },
    {
      "shelf": "I",
      "scene": "既存手当からの切替が目立つか心配（FAQ Q14）",
      "quote": "今の食事手当をやめて非課税に替えると、目立ちませんか？",
      "speaker": "人事・労組",
      "speakerRead": "従業員の見え方・納得感が論点。移行設計の具体策を求めている",
      "read": "切替自体が問題ではなく、告知・タイミング・公平性の設計が鍵。",
      "doIt": "賃上げ発表と同時切替で“目立たず”前向きに。EBP等カフェテリアは置換でなく追加共存も可。移行FAQ・説明会で「実質手取り増」を丁寧に説明。",
      "dont": "既存手当の突然廃止を告知なしで進める／課税→非課税の差額だけを強調して不安を煽る。",
      "freq": "中（デッキFAQ）",
      "status": "proven",
      "faqIds": [
        "Q14"
      ]
    },
    {
      "shelf": "CO",
      "scene": "エデンレッドの会社・実績を確認（FAQ Q15）",
      "quote": "エデンレッドってどんな会社？日本でどれくらいの実績？",
      "speaker": "経営・購買",
      "speakerRead": "ベンダー選定の最終確認。継続性・実績・支援体制を見ている",
      "read": "グローバル基盤＋日本40年・約4,000社・25万店が信頼の根拠。導入支援まで一気通貫。",
      "doIt": "世界44カ国・6,000万人／世界60年・日本40年。国内約4,000社・加盟店約25万店・利用率参考98%。規程・労使協定・説明会まで伴走とセットで語る。",
      "dont": "競合の機能細部比較に入る／実績数値を分析側の旧数字（4,500社等）で語る。",
      "freq": "中（デッキFAQ）",
      "status": "proven",
      "faqIds": [
        "Q15"
      ],
      "sources": [
        {
          "label": "エデンレッド公式",
          "url": "https://edenred.jp/"
        },
        {
          "label": "エデンレッド公式 チケットレストラン",
          "url": "https://edenred.jp/ticketrestaurant/"
        }
      ]
    }
  ]
}
